tb3py/__init__.py
tb3py/main.py
tb3py/pred.py
tb3py/vac_auto_multi.py
tb3py/tests/__init__.py
tb3py/tests/test_ptop.py
tb3py-2021.11.11.dist-info/LICENSE.md
tb3py-2021.11.11.dist-info/METADATA
tb3py-2021.11.11.dist-info/WHEEL
tb3py-2021.11.11.dist-info/top_level.txt
tb3py-2021.11.11.dist-info/RECORD
