Metadata-Version: 2.1
Name: tb3py
Version: 2021.11.11
Summary: tb3: an open-source software package for accurate and efficient electronic structure calculations using tight-binding (TB), including three-body interactions. https://pages.nist.gov/ThreeBodyTB.jl
Home-page: https://github.com/usnistgov/tb3py
Author: Kevin Garrity, Kamal Choudhary
Author-email: kevin.garrity@nist.gov
License: NIST
Platform: UNKNOWN
Classifier: Programming Language :: Python :: 3.7
Classifier: Development Status :: 4 - Beta
Classifier: Intended Audience :: Science/Research
Classifier: License :: OSI Approved :: MIT License
Classifier: Operating System :: OS Independent
Classifier: Topic :: Scientific/Engineering
License-File: LICENSE.md
Requires-Dist: requests (>=2.26.0)
Requires-Dist: numpy (>=1.19.5)
Requires-Dist: julia (>=0.5.6)
Requires-Dist: jarvis-tools
Requires-Dist: cython
Requires-Dist: pytest
Provides-Extra: jarvis-tools
Requires-Dist: jarvis-tools ; extra == 'jarvis-tools'
Provides-Extra: julia
Requires-Dist: julia ; extra == 'julia'
